{
  "ja": {
    "title": "アラビア語タイピング練習",
    "level1": "アルファベット",
    "level2": "基本単語",
    "level3": "時事用語",
    "level4": "諺・慣用句",
    "note_Sound": "※このゲームは開始と同時にBGMが鳴ります。音量にご注意ください。",
    "balloon": "マルハバン！ようこそ！<br>ゆっくりしていってね",
    "questionLabel": "問題",
    "enterHint": "入力が完了したらEnterキーを押してね",
    "correctAnswer": "正解だよ！すごいね！",
    "incorrectAnswer": "残念！正解は",
    "game_result": "結果",
    "game_score": "スコア",
    "resultTemplate": "10問中{correct}問正解です！",
    "elapsedTime": "かかった時間：{seconds}秒",
    "avgTime": "1文字あたり平均時間：{avg}秒",
    "msg_perfect": "満点です！すばらしい！",
    "msg_good": "いいですね！その調子でがんばってください！",
    "msg_retry": "また挑戦してね！",
    "game_return": "HOME",
    "btn_retry": "リトライ"

  },
  "en": {
    "title": "Arabic Typing Practice",
    "level1": "Alphabet",
    "level2": "Basic Words",
    "level3": "News Vocabulary",
    "level4": "Proverbs & Idioms",
    "note_Sound": "BGM starts when the game begins.Please check your volume settings.",
    "balloon": "Marhaban! Welcome!<br>Relax and enjoy your stay",
    "questionLabel": "Question",
    "enterHint": "Press Enter when you finish typing",
    "correctAnswer": "Correct! Great job!",
    "incorrectAnswer": "Oops! Correct answer is",
    "game_result": "Result",
    "game_score": "Score",
    "resultTemplate": "You got {correct} out of 10 correct!",
    "elapsedTime": "Time: {seconds} sec",
    "avgTime": "Average time: {avg} sec",
    "msg_perfect": "Perfect score! Excellent!",
    "msg_good": "Nice! Keep up the good work!",
    "msg_retry": "Try again next time!",
    "game_return": "HOME",
    "btn_retry": "Retry"

  }
}